productive_client_api/__init__.py
productive_client_api/productive.py
productive_client_api-0.1.18.dist-info/METADATA
productive_client_api-0.1.18.dist-info/WHEEL
productive_client_api-0.1.18.dist-info/RECORD
