Metadata-Version: 2.1
Name: productive-client-api
Version: 0.1.18
Summary: Client API for Productive system
License: MIT
Author: pawelkarbowniczek
Author-email: pawel.karbowniczek@cloudflight.io
Requires-Python: >=3.10,<4.0
Classifier: License :: OSI Approved :: MIT License
Classifier: Programming Language :: Python :: 3
Classifier: Programming Language :: Python :: 3.10
Classifier: Programming Language :: Python :: 3.11
Classifier: Programming Language :: Python :: 3.12
Requires-Dist: requests (>=2.32.3,<3.0.0)
